{
  "$schema": "https://frontmatter.codes/frontmatter.schema.json",
  "frontMatter.framework.id": "astro",
  "frontMatter.preview.host": "http://localhost:4322",
  "frontMatter.content.publicFolder": "public",
  "frontMatter.content.pageFolders": [
    {
      "path": "[[workspace]]/.github",
      "title": ".github"
    },
    {
      "path": "[[workspace]]/src/pages"
    },
    {
      "path": "[[workspace]]/.github/ISSUE_TEMPLATE"
    },
    {
      "title": "blog",
      "path": "[[workspace]]/src/data/blog"
    }
  ],
  "frontMatter.taxonomy.contentTypes": [
    {
      "name": "default",
      "pageBundle": false,
      "previewPath": "'blog'",
      "filePrefix": null,
      "clearEmpty": true,
      "fields": [
        {
          "title": "Title",
          "name": "title",
          "type": "string",
          "single": true
        },
        {
          "title": "Description",
          "name": "description",
          "type": "string"
        },
        {
          "title": "Publishing date",
          "name": "pubDate",
          "type": "datetime",
          "default": "{{now}}",
          "isPublishDate": true
        },
        {
          "title": "Content preview",
          "name": "heroImage",
          "type": "image",
          "isPreviewImage": true
        },
        {
          "title": "layout",
          "name": "layout",
          "type": "string"
        }
      ]
    },
    {
      "name": "now",
      "pageBundle": false,
      "fields": [
        {
          "title": "layout",
          "name": "layout",
          "type": "string"
        },
        {
          "title": "title",
          "name": "title",
          "type": "string"
        },
        {
          "title": "description",
          "name": "description",
          "type": "string"
        }
      ]
    }
  ],
  "frontMatter.git.enabled": true
}